[
  {
    "round": 0,
    "elapsed_sec": 141.02239274978638,
    "cumulative_comm_bytes": 218913600,
    "graph_updated": true,
    "graph_avg_degree": 18.2,
    "graph_spectral_gap": 4.23232806715507,
    "graph_is_connected": true,
    "global_accuracy": 0.11296399999999998,
    "per_client_accuracy": [
      0.1,
      0.1495,
      0.1704,
      0.1,
      0.1,
      0.1,
      0.1,
      0.1807,
      0.1518,
      0.1,
      0.1,
      0.1156,
      0.1,
      0.1,
      0.1,
      0.1238,
      0.1,
      0.1,
      0.1,
      0.1,
      0.1,
      0.1,
      0.1,
      0.1,
      0.1738,
      0.1249,
      0.1,
      0.1,
      0.1,
      0.1,
      0.118,
      0.1207,
      0.1,
      0.1,
      0.1016,
      0.1,
      0.1,
      0.1001,
      0.1446,
      0.1,
      0.1,
      0.1707,
      0.1,
      0.1,
      0.1,
      0.1019,
      0.1589,
      0.1,
      0.1412,
      0.1
    ],
    "accuracy_std": 0.02365928790137184,
    "worst_client_accuracy": 0.1,
    "global_loss": NaN,
    "honest_global_accuracy": 0.11620500000000003,
    "honest_accuracy_std": 0.02543977152020041,
    "honest_worst_accuracy": 0.1
  },
  {
    "round": 1,
    "elapsed_sec": 210.5519905090332,
    "cumulative_comm_bytes": 437827200,
    "graph_updated": false,
    "graph_avg_degree": 18.2,
    "graph_spectral_gap": 4.23232806715507,
    "graph_is_connected": true
  },
  {
    "round": 2,
    "elapsed_sec": 274.6094570159912,
    "cumulative_comm_bytes": 656740800,
    "graph_updated": false,
    "graph_avg_degree": 18.2,
    "graph_spectral_gap": 4.23232806715507,
    "graph_is_connected": true
  },
  {
    "round": 3,
    "elapsed_sec": 333.968554019928,
    "cumulative_comm_bytes": 875654400,
    "graph_updated": false,
    "graph_avg_degree": 18.2,
    "graph_spectral_gap": 4.23232806715507,
    "graph_is_connected": true
  },
  {
    "round": 4,
    "elapsed_sec": 394.0214138031006,
    "cumulative_comm_bytes": 1094568000,
    "graph_updated": false,
    "graph_avg_degree": 18.2,
    "graph_spectral_gap": 4.23232806715507,
    "graph_is_connected": true
  },
  {
    "round": 5,
    "elapsed_sec": 537.7722065448761,
    "cumulative_comm_bytes": 1313481600,
    "graph_updated": true,
    "graph_avg_degree": 17.68,
    "graph_spectral_gap": 3.8230486729127806,
    "graph_is_connected": true,
    "global_accuracy": 0.10922599999999998,
    "per_client_accuracy": [
      0.1121,
      0.1,
      0.1,
      0.1,
      0.1,
      0.1,
      0.1,
      0.1,
      0.1016,
      0.1,
      0.1278,
      0.1036,
      0.1,
      0.1268,
      0.1,
      0.1641,
      0.1,
      0.1602,
      0.1,
      0.1,
      0.1,
      0.1479,
      0.1,
      0.1021,
      0.1,
      0.1,
      0.1184,
      0.1,
      0.1,
      0.1412,
      0.1207,
      0.1314,
      0.1,
      0.1,
      0.1,
      0.1,
      0.1003,
      0.1,
      0.1,
      0.1,
      0.1,
      0.1,
      0.1,
      0.1,
      0.1,
      0.1,
      0.1,
      0.1,
      0.2031,
      0.1
    ],
    "accuracy_std": 0.020740721395361348,
    "worst_client_accuracy": 0.1,
    "global_loss": NaN,
    "honest_global_accuracy": 0.11153249999999999,
    "honest_accuracy_std": 0.022608011715982455,
    "honest_worst_accuracy": 0.1
  },
  {
    "round": 6,
    "elapsed_sec": 610.3913943767548,
    "cumulative_comm_bytes": 1532395200,
    "graph_updated": false,
    "graph_avg_degree": 17.68,
    "graph_spectral_gap": 3.8230486729127806,
    "graph_is_connected": true
  },
  {
    "round": 7,
    "elapsed_sec": 673.5231173038483,
    "cumulative_comm_bytes": 1751308800,
    "graph_updated": false,
    "graph_avg_degree": 17.68,
    "graph_spectral_gap": 3.8230486729127806,
    "graph_is_connected": true
  },
  {
    "round": 8,
    "elapsed_sec": 732.5620121955872,
    "cumulative_comm_bytes": 1970222400,
    "graph_updated": false,
    "graph_avg_degree": 17.68,
    "graph_spectral_gap": 3.8230486729127806,
    "graph_is_connected": true
  },
  {
    "round": 9,
    "elapsed_sec": 791.637482881546,
    "cumulative_comm_bytes": 2189136000,
    "graph_updated": false,
    "graph_avg_degree": 17.68,
    "graph_spectral_gap": 3.8230486729127806,
    "graph_is_connected": true
  },
  {
    "round": 10,
    "elapsed_sec": 935.3850226402283,
    "cumulative_comm_bytes": 2408049600,
    "graph_updated": true,
    "graph_avg_degree": 17.28,
    "graph_spectral_gap": 3.6721106548679328,
    "graph_is_connected": true,
    "global_accuracy": 0.11657400000000001,
    "per_client_accuracy": [
      0.1,
      0.1,
      0.1,
      0.1,
      0.1,
      0.1,
      0.1,
      0.1,
      0.2285,
      0.1,
      0.1,
      0.1,
      0.1835,
      0.1839,
      0.1,
      0.1,
      0.1,
      0.1092,
      0.1465,
      0.1,
      0.1,
      0.1,
      0.1,
      0.115,
      0.1964,
      0.1575,
      0.1,
      0.1,
      0.1,
      0.1,
      0.1,
      0.1,
      0.1,
      0.1055,
      0.1714,
      0.1,
      0.1404,
      0.1,
      0.1,
      0.1,
      0.1,
      0.1802,
      0.1809,
      0.1,
      0.1,
      0.1,
      0.1,
      0.1,
      0.1298,
      0.1
    ],
    "accuracy_std": 0.03239913461807274,
    "worst_client_accuracy": 0.1,
    "global_loss": NaN,
    "honest_global_accuracy": 0.12057999999999999,
    "honest_accuracy_std": 0.0350885893133366,
    "honest_worst_accuracy": 0.1
  },
  {
    "round": 11,
    "elapsed_sec": 994.844521522522,
    "cumulative_comm_bytes": 2626963200,
    "graph_updated": false,
    "graph_avg_degree": 17.28,
    "graph_spectral_gap": 3.6721106548679328,
    "graph_is_connected": true
  },
  {
    "round": 12,
    "elapsed_sec": 1057.8651900291443,
    "cumulative_comm_bytes": 2845876800,
    "graph_updated": false,
    "graph_avg_degree": 17.28,
    "graph_spectral_gap": 3.6721106548679328,
    "graph_is_connected": true
  },
  {
    "round": 13,
    "elapsed_sec": 1116.6979081630707,
    "cumulative_comm_bytes": 3064790400,
    "graph_updated": false,
    "graph_avg_degree": 17.28,
    "graph_spectral_gap": 3.6721106548679328,
    "graph_is_connected": true
  },
  {
    "round": 14,
    "elapsed_sec": 1175.812834739685,
    "cumulative_comm_bytes": 3283704000,
    "graph_updated": false,
    "graph_avg_degree": 17.28,
    "graph_spectral_gap": 3.6721106548679328,
    "graph_is_connected": true
  },
  {
    "round": 15,
    "elapsed_sec": 1316.6971197128296,
    "cumulative_comm_bytes": 3502617600,
    "graph_updated": true,
    "graph_avg_degree": 16.56,
    "graph_spectral_gap": 3.138471600204962,
    "graph_is_connected": true,
    "global_accuracy": 0.10116799999999998,
    "per_client_accuracy": [
      0.1,
      0.1,
      0.1,
      0.1,
      0.1,
      0.1,
      0.1,
      0.1001,
      0.1,
      0.1,
      0.1,
      0.1,
      0.1229,
      0.1132,
      0.1,
      0.1,
      0.1,
      0.1,
      0.1,
      0.1,
      0.1,
      0.1124,
      0.1,
      0.1,
      0.1,
      0.1,
      0.1,
      0.1,
      0.1,
      0.1,
      0.1,
      0.1,
      0.1,
      0.1,
      0.1,
      0.1,
      0.1,
      0.1,
      0.1,
      0.1,
      0.1,
      0.1079,
      0.1,
      0.1,
      0.1,
      0.1,
      0.1019,
      0.1,
      0.1,
      0.1
    ],
    "accuracy_std": 0.004123660509789812,
    "worst_client_accuracy": 0.1,
    "global_loss": NaN,
    "honest_global_accuracy": 0.10146,
    "honest_accuracy_std": 0.004563923750458587,
    "honest_worst_accuracy": 0.1
  },
  {
    "round": 16,
    "elapsed_sec": 1390.2604911327362,
    "cumulative_comm_bytes": 3721531200,
    "graph_updated": false,
    "graph_avg_degree": 16.56,
    "graph_spectral_gap": 3.138471600204962,
    "graph_is_connected": true
  },
  {
    "round": 17,
    "elapsed_sec": 1450.9298510551453,
    "cumulative_comm_bytes": 3940444800,
    "graph_updated": false,
    "graph_avg_degree": 16.56,
    "graph_spectral_gap": 3.138471600204962,
    "graph_is_connected": true
  },
  {
    "round": 18,
    "elapsed_sec": 1509.2304737567902,
    "cumulative_comm_bytes": 4159358400,
    "graph_updated": false,
    "graph_avg_degree": 16.56,
    "graph_spectral_gap": 3.138471600204962,
    "graph_is_connected": true
  },
  {
    "round": 19,
    "elapsed_sec": 1567.2824308872223,
    "cumulative_comm_bytes": 4378272000,
    "graph_updated": false,
    "graph_avg_degree": 16.56,
    "graph_spectral_gap": 3.138471600204962,
    "graph_is_connected": true
  },
  {
    "round": 20,
    "elapsed_sec": 1711.3420572280884,
    "cumulative_comm_bytes": 4597185600,
    "graph_updated": true,
    "graph_avg_degree": 15.0,
    "graph_spectral_gap": 2.2980209487298096,
    "graph_is_connected": true,
    "global_accuracy": 0.10985199999999999,
    "per_client_accuracy": [
      0.1033,
      0.1,
      0.1,
      0.1,
      0.1,
      0.1,
      0.1,
      0.1,
      0.1,
      0.1,
      0.1831,
      0.1,
      0.1725,
      0.1833,
      0.1,
      0.1,
      0.1,
      0.1,
      0.1,
      0.1,
      0.1,
      0.1007,
      0.1,
      0.1,
      0.1075,
      0.1335,
      0.1,
      0.1,
      0.1,
      0.1233,
      0.1,
      0.1001,
      0.1,
      0.1,
      0.1001,
      0.1002,
      0.1,
      0.1,
      0.1,
      0.1,
      0.1,
      0.1798,
      0.1,
      0.1,
      0.1,
      0.1,
      0.1444,
      0.1,
      0.1608,
      0.1
    ],
    "accuracy_std": 0.0236713011049245,
    "worst_client_accuracy": 0.1,
    "global_loss": NaN,
    "honest_global_accuracy": 0.11231499999999998,
    "honest_accuracy_std": 0.02588592812707321,
    "honest_worst_accuracy": 0.1
  },
  {
    "round": 21,
    "elapsed_sec": 1785.031882762909,
    "cumulative_comm_bytes": 4816099200,
    "graph_updated": false,
    "graph_avg_degree": 15.0,
    "graph_spectral_gap": 2.2980209487298096,
    "graph_is_connected": true
  },
  {
    "round": 22,
    "elapsed_sec": 1844.9043605327606,
    "cumulative_comm_bytes": 5035012800,
    "graph_updated": false,
    "graph_avg_degree": 15.0,
    "graph_spectral_gap": 2.2980209487298096,
    "graph_is_connected": true
  },
  {
    "round": 23,
    "elapsed_sec": 1902.5563552379608,
    "cumulative_comm_bytes": 5253926400,
    "graph_updated": false,
    "graph_avg_degree": 15.0,
    "graph_spectral_gap": 2.2980209487298096,
    "graph_is_connected": true
  },
  {
    "round": 24,
    "elapsed_sec": 1960.3426129817963,
    "cumulative_comm_bytes": 5472840000,
    "graph_updated": false,
    "graph_avg_degree": 15.0,
    "graph_spectral_gap": 2.2980209487298096,
    "graph_is_connected": true
  },
  {
    "round": 25,
    "elapsed_sec": 2098.885698080063,
    "cumulative_comm_bytes": 5691753600,
    "graph_updated": true,
    "graph_avg_degree": 14.56,
    "graph_spectral_gap": 2.0429593578811787,
    "graph_is_connected": true,
    "global_accuracy": 0.111772,
    "per_client_accuracy": [
      0.1,
      0.1,
      0.1,
      0.1,
      0.1,
      0.1,
      0.1,
      0.177,
      0.1,
      0.1,
      0.1274,
      0.1,
      0.1555,
      0.1316,
      0.1425,
      0.1,
      0.1,
      0.1631,
      0.1,
      0.1,
      0.1,
      0.132,
      0.1,
      0.1,
      0.1046,
      0.1,
      0.1,
      0.1,
      0.1,
      0.1,
      0.1,
      0.165,
      0.1,
      0.1299,
      0.1015,
      0.1165,
      0.1,
      0.1,
      0.1,
      0.1,
      0.1,
      0.1772,
      0.1,
      0.1001,
      0.1,
      0.1,
      0.1001,
      0.1,
      0.1646,
      0.1
    ],
    "accuracy_std": 0.022886293190466644,
    "worst_client_accuracy": 0.1,
    "global_loss": NaN,
    "honest_global_accuracy": 0.1139675,
    "honest_accuracy_std": 0.024708534836165415,
    "honest_worst_accuracy": 0.1
  },
  {
    "round": 26,
    "elapsed_sec": 2171.3524334430695,
    "cumulative_comm_bytes": 5910667200,
    "graph_updated": false,
    "graph_avg_degree": 14.56,
    "graph_spectral_gap": 2.0429593578811787,
    "graph_is_connected": true
  },
  {
    "round": 27,
    "elapsed_sec": 2231.4720153808594,
    "cumulative_comm_bytes": 6129580800,
    "graph_updated": false,
    "graph_avg_degree": 14.56,
    "graph_spectral_gap": 2.0429593578811787,
    "graph_is_connected": true
  },
  {
    "round": 28,
    "elapsed_sec": 2288.9166679382324,
    "cumulative_comm_bytes": 6348494400,
    "graph_updated": false,
    "graph_avg_degree": 14.56,
    "graph_spectral_gap": 2.0429593578811787,
    "graph_is_connected": true
  },
  {
    "round": 29,
    "elapsed_sec": 2346.3818068504333,
    "cumulative_comm_bytes": 6567408000,
    "graph_updated": false,
    "graph_avg_degree": 14.56,
    "graph_spectral_gap": 2.0429593578811787,
    "graph_is_connected": true
  },
  {
    "round": 30,
    "elapsed_sec": 2484.909764766693,
    "cumulative_comm_bytes": 6786321600,
    "graph_updated": true,
    "graph_avg_degree": 14.52,
    "graph_spectral_gap": 1.7499553588719623,
    "graph_is_connected": true,
    "global_accuracy": 0.11094399999999999,
    "per_client_accuracy": [
      0.1,
      0.1,
      0.1,
      0.1,
      0.1,
      0.1,
      0.1,
      0.1713,
      0.1336,
      0.1,
      0.1001,
      0.1,
      0.115,
      0.2087,
      0.1,
      0.1,
      0.1,
      0.1,
      0.1057,
      0.1,
      0.1,
      0.1174,
      0.1,
      0.1,
      0.1,
      0.1533,
      0.1,
      0.1,
      0.1,
      0.1707,
      0.1,
      0.1001,
      0.1,
      0.1188,
      0.1003,
      0.1,
      0.1,
      0.1781,
      0.1,
      0.1,
      0.1,
      0.1,
      0.1,
      0.1,
      0.1,
      0.1,
      0.1004,
      0.1009,
      0.1728,
      0.1
    ],
    "accuracy_std": 0.025374547562468968,
    "worst_client_accuracy": 0.1,
    "global_loss": NaN,
    "honest_global_accuracy": 0.11321,
    "honest_accuracy_std": 0.027770639171614323,
    "honest_worst_accuracy": 0.1
  },
  {
    "round": 31,
    "elapsed_sec": 2557.128645658493,
    "cumulative_comm_bytes": 7005235200,
    "graph_updated": false,
    "graph_avg_degree": 14.52,
    "graph_spectral_gap": 1.7499553588719623,
    "graph_is_connected": true
  },
  {
    "round": 32,
    "elapsed_sec": 2617.774685382843,
    "cumulative_comm_bytes": 7224148800,
    "graph_updated": false,
    "graph_avg_degree": 14.52,
    "graph_spectral_gap": 1.7499553588719623,
    "graph_is_connected": true
  },
  {
    "round": 33,
    "elapsed_sec": 2675.296451330185,
    "cumulative_comm_bytes": 7443062400,
    "graph_updated": false,
    "graph_avg_degree": 14.52,
    "graph_spectral_gap": 1.7499553588719623,
    "graph_is_connected": true
  },
  {
    "round": 34,
    "elapsed_sec": 2732.939354658127,
    "cumulative_comm_bytes": 7661976000,
    "graph_updated": false,
    "graph_avg_degree": 14.52,
    "graph_spectral_gap": 1.7499553588719623,
    "graph_is_connected": true
  },
  {
    "round": 35,
    "elapsed_sec": 2873.786744117737,
    "cumulative_comm_bytes": 7880889600,
    "graph_updated": true,
    "graph_avg_degree": 15.32,
    "graph_spectral_gap": 1.770554891075622,
    "graph_is_connected": true,
    "global_accuracy": 0.11083999999999998,
    "per_client_accuracy": [
      0.1,
      0.1,
      0.1,
      0.1,
      0.1,
      0.1,
      0.1,
      0.1654,
      0.1,
      0.1,
      0.1319,
      0.1055,
      0.1,
      0.1,
      0.1,
      0.1263,
      0.1,
      0.1,
      0.1101,
      0.1,
      0.1,
      0.1,
      0.1,
      0.1,
      0.1,
      0.1,
      0.1,
      0.1,
      0.1,
      0.1,
      0.1,
      0.18,
      0.1,
      0.1,
      0.1,
      0.1,
      0.1,
      0.1832,
      0.1,
      0.1,
      0.1336,
      0.1611,
      0.1771,
      0.1,
      0.1,
      0.1,
      0.1,
      0.1,
      0.1678,
      0.1
    ],
    "accuracy_std": 0.024070355211338282,
    "worst_client_accuracy": 0.1,
    "global_loss": NaN,
    "honest_global_accuracy": 0.11355,
    "honest_accuracy_std": 0.026220354688676503,
    "honest_worst_accuracy": 0.1
  },
  {
    "round": 36,
    "elapsed_sec": 2943.010056734085,
    "cumulative_comm_bytes": 8099803200,
    "graph_updated": false,
    "graph_avg_degree": 15.32,
    "graph_spectral_gap": 1.770554891075622,
    "graph_is_connected": true
  },
  {
    "round": 37,
    "elapsed_sec": 3008.5441682338715,
    "cumulative_comm_bytes": 8318716800,
    "graph_updated": false,
    "graph_avg_degree": 15.32,
    "graph_spectral_gap": 1.770554891075622,
    "graph_is_connected": true
  },
  {
    "round": 38,
    "elapsed_sec": 3065.8073563575745,
    "cumulative_comm_bytes": 8537630400,
    "graph_updated": false,
    "graph_avg_degree": 15.32,
    "graph_spectral_gap": 1.770554891075622,
    "graph_is_connected": true
  },
  {
    "round": 39,
    "elapsed_sec": 3123.071832180023,
    "cumulative_comm_bytes": 8756544000,
    "graph_updated": false,
    "graph_avg_degree": 15.32,
    "graph_spectral_gap": 1.770554891075622,
    "graph_is_connected": true
  },
  {
    "round": 40,
    "elapsed_sec": 3265.0535311698914,
    "cumulative_comm_bytes": 8975457600,
    "graph_updated": true,
    "graph_avg_degree": 15.0,
    "graph_spectral_gap": 1.8031002157051432,
    "graph_is_connected": true,
    "global_accuracy": 0.11255199999999999,
    "per_client_accuracy": [
      0.1637,
      0.1,
      0.1,
      0.1,
      0.1,
      0.1,
      0.1743,
      0.1669,
      0.1573,
      0.1,
      0.1267,
      0.1,
      0.1,
      0.1103,
      0.1,
      0.1,
      0.1,
      0.1,
      0.1112,
      0.1,
      0.1,
      0.1,
      0.1177,
      0.101,
      0.1657,
      0.1,
      0.1,
      0.1175,
      0.1,
      0.1,
      0.1,
      0.1684,
      0.1,
      0.1005,
      0.1,
      0.1,
      0.1,
      0.1,
      0.1,
      0.1,
      0.1355,
      0.142,
      0.1,
      0.1,
      0.1,
      0.1,
      0.1689,
      0.1,
      0.1,
      0.1
    ],
    "accuracy_std": 0.02357590498793206,
    "worst_client_accuracy": 0.1,
    "global_loss": NaN,
    "honest_global_accuracy": 0.11567749999999999,
    "honest_accuracy_std": 0.025415147919105246,
    "honest_worst_accuracy": 0.1
  },
  {
    "round": 41,
    "elapsed_sec": 3328.902253627777,
    "cumulative_comm_bytes": 9194371200,
    "graph_updated": false,
    "graph_avg_degree": 15.0,
    "graph_spectral_gap": 1.8031002157051432,
    "graph_is_connected": true
  },
  {
    "round": 42,
    "elapsed_sec": 3398.3825924396515,
    "cumulative_comm_bytes": 9413284800,
    "graph_updated": false,
    "graph_avg_degree": 15.0,
    "graph_spectral_gap": 1.8031002157051432,
    "graph_is_connected": true
  },
  {
    "round": 43,
    "elapsed_sec": 3455.547289133072,
    "cumulative_comm_bytes": 9632198400,
    "graph_updated": false,
    "graph_avg_degree": 15.0,
    "graph_spectral_gap": 1.8031002157051432,
    "graph_is_connected": true
  },
  {
    "round": 44,
    "elapsed_sec": 3512.8708233833313,
    "cumulative_comm_bytes": 9851112000,
    "graph_updated": false,
    "graph_avg_degree": 15.0,
    "graph_spectral_gap": 1.8031002157051432,
    "graph_is_connected": true
  },
  {
    "round": 45,
    "elapsed_sec": 3652.9062411785126,
    "cumulative_comm_bytes": 10070025600,
    "graph_updated": true,
    "graph_avg_degree": 15.04,
    "graph_spectral_gap": 1.9016828135809323,
    "graph_is_connected": true,
    "global_accuracy": 0.12122200000000001,
    "per_client_accuracy": [
      0.1,
      0.1,
      0.1,
      0.1,
      0.1,
      0.1,
      0.1,
      0.1,
      0.1838,
      0.1,
      0.1875,
      0.1357,
      0.138,
      0.1827,
      0.1,
      0.124,
      0.1,
      0.1865,
      0.1,
      0.1,
      0.1,
      0.1756,
      0.1,
      0.1,
      0.1741,
      0.1002,
      0.1,
      0.1173,
      0.1,
      0.1813,
      0.1269,
      0.1,
      0.1,
      0.1002,
      0.176,
      0.1,
      0.1,
      0.1389,
      0.1,
      0.1,
      0.1,
      0.1,
      0.1472,
      0.1,
      0.1,
      0.1,
      0.2234,
      0.1,
      0.1618,
      0.1
    ],
    "accuracy_std": 0.033816784530762235,
    "worst_client_accuracy": 0.1,
    "global_loss": NaN,
    "honest_global_accuracy": 0.1265225,
    "honest_accuracy_std": 0.03590252419747113,
    "honest_worst_accuracy": 0.1
  },
  {
    "round": 46,
    "elapsed_sec": 3714.4386987686157,
    "cumulative_comm_bytes": 10288939200,
    "graph_updated": false,
    "graph_avg_degree": 15.04,
    "graph_spectral_gap": 1.9016828135809323,
    "graph_is_connected": true
  },
  {
    "round": 47,
    "elapsed_sec": 3785.726952791214,
    "cumulative_comm_bytes": 10507852800,
    "graph_updated": false,
    "graph_avg_degree": 15.04,
    "graph_spectral_gap": 1.9016828135809323,
    "graph_is_connected": true
  },
  {
    "round": 48,
    "elapsed_sec": 3842.9806332588196,
    "cumulative_comm_bytes": 10726766400,
    "graph_updated": false,
    "graph_avg_degree": 15.04,
    "graph_spectral_gap": 1.9016828135809323,
    "graph_is_connected": true
  },
  {
    "round": 49,
    "elapsed_sec": 3900.1413173675537,
    "cumulative_comm_bytes": 10945680000,
    "graph_updated": false,
    "graph_avg_degree": 15.04,
    "graph_spectral_gap": 1.9016828135809323,
    "graph_is_connected": true
  },
  {
    "round": 50,
    "elapsed_sec": 4039.789207458496,
    "cumulative_comm_bytes": 11164593600,
    "graph_updated": true,
    "graph_avg_degree": 15.28,
    "graph_spectral_gap": 2.2980552858044487,
    "graph_is_connected": true,
    "global_accuracy": 0.10926399999999997,
    "per_client_accuracy": [
      0.1,
      0.1,
      0.1,
      0.1,
      0.1,
      0.1,
      0.1,
      0.1523,
      0.1,
      0.1,
      0.1,
      0.1,
      0.1,
      0.1007,
      0.1,
      0.1,
      0.1009,
      0.165,
      0.1,
      0.1,
      0.1002,
      0.175,
      0.1,
      0.1,
      0.1,
      0.1001,
      0.1,
      0.1012,
      0.1,
      0.1739,
      0.1,
      0.1152,
      0.1,
      0.1,
      0.1132,
      0.1,
      0.1,
      0.1782,
      0.1,
      0.1,
      0.1,
      0.1,
      0.1148,
      0.1,
      0.1,
      0.1,
      0.1725,
      0.1,
      0.1,
      0.1
    ],
    "accuracy_std": 0.022695380675370923,
    "worst_client_accuracy": 0.1,
    "global_loss": NaN,
    "honest_global_accuracy": 0.11157999999999998,
    "honest_accuracy_std": 0.024840110708287913,
    "honest_worst_accuracy": 0.1
  },
  {
    "round": 51,
    "elapsed_sec": 4098.248478651047,
    "cumulative_comm_bytes": 11383507200,
    "graph_updated": false,
    "graph_avg_degree": 15.28,
    "graph_spectral_gap": 2.2980552858044487,
    "graph_is_connected": true
  },
  {
    "round": 52,
    "elapsed_sec": 4171.1452577114105,
    "cumulative_comm_bytes": 11602420800,
    "graph_updated": false,
    "graph_avg_degree": 15.28,
    "graph_spectral_gap": 2.2980552858044487,
    "graph_is_connected": true
  },
  {
    "round": 53,
    "elapsed_sec": 4228.271132469177,
    "cumulative_comm_bytes": 11821334400,
    "graph_updated": false,
    "graph_avg_degree": 15.28,
    "graph_spectral_gap": 2.2980552858044487,
    "graph_is_connected": true
  },
  {
    "round": 54,
    "elapsed_sec": 4285.5492424964905,
    "cumulative_comm_bytes": 12040248000,
    "graph_updated": false,
    "graph_avg_degree": 15.28,
    "graph_spectral_gap": 2.2980552858044487,
    "graph_is_connected": true
  },
  {
    "round": 55,
    "elapsed_sec": 4423.976256608963,
    "cumulative_comm_bytes": 12259161600,
    "graph_updated": true,
    "graph_avg_degree": 14.4,
    "graph_spectral_gap": 2.1008963466870383,
    "graph_is_connected": true,
    "global_accuracy": 0.11405599999999999,
    "per_client_accuracy": [
      0.1,
      0.1,
      0.1,
      0.1,
      0.1,
      0.1,
      0.1,
      0.1497,
      0.1,
      0.1,
      0.1336,
      0.1,
      0.1816,
      0.1873,
      0.1,
      0.1,
      0.1,
      0.1112,
      0.1,
      0.1,
      0.1,
      0.1,
      0.1,
      0.1,
      0.1234,
      0.1858,
      0.1,
      0.1,
      0.1,
      0.1291,
      0.1,
      0.1796,
      0.1,
      0.1,
      0.105,
      0.2044,
      0.1,
      0.1018,
      0.1,
      0.1,
      0.1,
      0.1,
      0.1113,
      0.1264,
      0.1,
      0.1,
      0.1,
      0.1,
      0.1726,
      0.1
    ],
    "accuracy_std": 0.028369336685936105,
    "worst_client_accuracy": 0.1,
    "global_loss": NaN,
    "honest_global_accuracy": 0.11757,
    "honest_accuracy_std": 0.03072918970620605,
    "honest_worst_accuracy": 0.1
  },
  {
    "round": 56,
    "elapsed_sec": 4481.639659643173,
    "cumulative_comm_bytes": 12478075200,
    "graph_updated": false,
    "graph_avg_degree": 14.4,
    "graph_spectral_gap": 2.1008963466870383,
    "graph_is_connected": true
  },
  {
    "round": 57,
    "elapsed_sec": 4554.545194387436,
    "cumulative_comm_bytes": 12696988800,
    "graph_updated": false,
    "graph_avg_degree": 14.4,
    "graph_spectral_gap": 2.1008963466870383,
    "graph_is_connected": true
  },
  {
    "round": 58,
    "elapsed_sec": 4612.63721871376,
    "cumulative_comm_bytes": 12915902400,
    "graph_updated": false,
    "graph_avg_degree": 14.4,
    "graph_spectral_gap": 2.1008963466870383,
    "graph_is_connected": true
  },
  {
    "round": 59,
    "elapsed_sec": 4670.4031546115875,
    "cumulative_comm_bytes": 13134816000,
    "graph_updated": false,
    "graph_avg_degree": 14.4,
    "graph_spectral_gap": 2.1008963466870383,
    "graph_is_connected": true
  },
  {
    "round": 60,
    "elapsed_sec": 4813.208807229996,
    "cumulative_comm_bytes": 13353729600,
    "graph_updated": true,
    "graph_avg_degree": 15.44,
    "graph_spectral_gap": 2.106980856710395,
    "graph_is_connected": true,
    "global_accuracy": 0.11266999999999998,
    "per_client_accuracy": [
      0.1,
      0.1,
      0.1,
      0.1,
      0.1,
      0.1,
      0.1,
      0.1357,
      0.1962,
      0.1,
      0.1854,
      0.1,
      0.1,
      0.1,
      0.1,
      0.1,
      0.1626,
      0.1849,
      0.1695,
      0.1,
      0.1001,
      0.1003,
      0.1,
      0.1,
      0.1086,
      0.1722,
      0.1,
      0.1,
      0.1,
      0.1,
      0.1,
      0.1742,
      0.1,
      0.1,
      0.1,
      0.1154,
      0.1,
      0.1268,
      0.1,
      0.1,
      0.1,
      0.1,
      0.1016,
      0.1,
      0.1,
      0.1,
      0.1,
      0.1,
      0.1,
      0.1
    ],
    "accuracy_std": 0.027387283545470514,
    "worst_client_accuracy": 0.1,
    "global_loss": NaN,
    "honest_global_accuracy": 0.1158375,
    "honest_accuracy_std": 0.029789492170058895,
    "honest_worst_accuracy": 0.1
  },
  {
    "round": 61,
    "elapsed_sec": 4870.743426561356,
    "cumulative_comm_bytes": 13572643200,
    "graph_updated": false,
    "graph_avg_degree": 15.44,
    "graph_spectral_gap": 2.106980856710395,
    "graph_is_connected": true
  },
  {
    "round": 62,
    "elapsed_sec": 4944.034796476364,
    "cumulative_comm_bytes": 13791556800,
    "graph_updated": false,
    "graph_avg_degree": 15.44,
    "graph_spectral_gap": 2.106980856710395,
    "graph_is_connected": true
  },
  {
    "round": 63,
    "elapsed_sec": 5002.396190404892,
    "cumulative_comm_bytes": 14010470400,
    "graph_updated": false,
    "graph_avg_degree": 15.44,
    "graph_spectral_gap": 2.106980856710395,
    "graph_is_connected": true
  },
  {
    "round": 64,
    "elapsed_sec": 5059.896546363831,
    "cumulative_comm_bytes": 14229384000,
    "graph_updated": false,
    "graph_avg_degree": 15.44,
    "graph_spectral_gap": 2.106980856710395,
    "graph_is_connected": true
  },
  {
    "round": 65,
    "elapsed_sec": 5198.153596878052,
    "cumulative_comm_bytes": 14448297600,
    "graph_updated": true,
    "graph_avg_degree": 14.24,
    "graph_spectral_gap": 2.180321918670089,
    "graph_is_connected": true,
    "global_accuracy": 0.11310599999999997,
    "per_client_accuracy": [
      0.1,
      0.1,
      0.1,
      0.1,
      0.1,
      0.1,
      0.1,
      0.1636,
      0.1,
      0.1,
      0.1557,
      0.1,
      0.1458,
      0.1,
      0.1,
      0.1,
      0.161,
      0.105,
      0.1928,
      0.1,
      0.1,
      0.1,
      0.1,
      0.1,
      0.1,
      0.1556,
      0.1,
      0.1,
      0.1,
      0.1666,
      0.1,
      0.1,
      0.1,
      0.1,
      0.1,
      0.1,
      0.1,
      0.1952,
      0.1,
      0.1,
      0.1001,
      0.1,
      0.1332,
      0.1,
      0.1,
      0.1,
      0.1282,
      0.1,
      0.1525,
      0.1
    ],
    "accuracy_std": 0.026175663582801486,
    "worst_client_accuracy": 0.1,
    "global_loss": NaN,
    "honest_global_accuracy": 0.11638249999999999,
    "honest_accuracy_std": 0.028333362732827883,
    "honest_worst_accuracy": 0.1
  },
  {
    "round": 66,
    "elapsed_sec": 5255.621520280838,
    "cumulative_comm_bytes": 14667211200,
    "graph_updated": false,
    "graph_avg_degree": 14.24,
    "graph_spectral_gap": 2.180321918670089,
    "graph_is_connected": true
  },
  {
    "round": 67,
    "elapsed_sec": 5312.523189783096,
    "cumulative_comm_bytes": 14886124800,
    "graph_updated": false,
    "graph_avg_degree": 14.24,
    "graph_spectral_gap": 2.180321918670089,
    "graph_is_connected": true
  },
  {
    "round": 68,
    "elapsed_sec": 5374.122235298157,
    "cumulative_comm_bytes": 15105038400,
    "graph_updated": false,
    "graph_avg_degree": 14.24,
    "graph_spectral_gap": 2.180321918670089,
    "graph_is_connected": true
  },
  {
    "round": 69,
    "elapsed_sec": 5431.327677965164,
    "cumulative_comm_bytes": 15323952000,
    "graph_updated": false,
    "graph_avg_degree": 14.24,
    "graph_spectral_gap": 2.180321918670089,
    "graph_is_connected": true
  },
  {
    "round": 70,
    "elapsed_sec": 5567.906520366669,
    "cumulative_comm_bytes": 15542865600,
    "graph_updated": true,
    "graph_avg_degree": 15.4,
    "graph_spectral_gap": 2.6499631716307563,
    "graph_is_connected": true,
    "global_accuracy": 0.11292599999999997,
    "per_client_accuracy": [
      0.1,
      0.1,
      0.1,
      0.1,
      0.1,
      0.1,
      0.1,
      0.1706,
      0.1565,
      0.1,
      0.1,
      0.1,
      0.1036,
      0.163,
      0.1,
      0.1,
      0.1098,
      0.1298,
      0.1,
      0.1,
      0.1,
      0.1616,
      0.1,
      0.1,
      0.1098,
      0.1893,
      0.1,
      0.1,
      0.1,
      0.1494,
      0.1,
      0.1,
      0.1,
      0.1,
      0.1,
      0.1543,
      0.1,
      0.1798,
      0.1,
      0.1,
      0.1,
      0.1,
      0.1,
      0.1,
      0.1,
      0.1,
      0.1002,
      0.1,
      0.1686,
      0.1
    ],
    "accuracy_std": 0.02573579460595689,
    "worst_client_accuracy": 0.1,
    "global_loss": NaN,
    "honest_global_accuracy": 0.1161575,
    "honest_accuracy_std": 0.027851408290246293,
    "honest_worst_accuracy": 0.1
  },
  {
    "round": 71,
    "elapsed_sec": 5625.156368732452,
    "cumulative_comm_bytes": 15761779200,
    "graph_updated": false,
    "graph_avg_degree": 15.4,
    "graph_spectral_gap": 2.6499631716307563,
    "graph_is_connected": true
  },
  {
    "round": 72,
    "elapsed_sec": 5694.843798160553,
    "cumulative_comm_bytes": 15980692800,
    "graph_updated": false,
    "graph_avg_degree": 15.4,
    "graph_spectral_gap": 2.6499631716307563,
    "graph_is_connected": true
  },
  {
    "round": 73,
    "elapsed_sec": 5757.753131151199,
    "cumulative_comm_bytes": 16199606400,
    "graph_updated": false,
    "graph_avg_degree": 15.4,
    "graph_spectral_gap": 2.6499631716307563,
    "graph_is_connected": true
  },
  {
    "round": 74,
    "elapsed_sec": 5815.948610067368,
    "cumulative_comm_bytes": 16418520000,
    "graph_updated": false,
    "graph_avg_degree": 15.4,
    "graph_spectral_gap": 2.6499631716307563,
    "graph_is_connected": true
  },
  {
    "round": 75,
    "elapsed_sec": 5956.333259820938,
    "cumulative_comm_bytes": 16637433600,
    "graph_updated": true,
    "graph_avg_degree": 14.76,
    "graph_spectral_gap": 2.4996758830522374,
    "graph_is_connected": true,
    "global_accuracy": 0.108644,
    "per_client_accuracy": [
      0.1,
      0.1,
      0.1,
      0.1,
      0.1,
      0.1,
      0.1,
      0.1398,
      0.1,
      0.1,
      0.1001,
      0.1,
      0.1743,
      0.1823,
      0.1,
      0.1,
      0.1155,
      0.1422,
      0.1,
      0.1,
      0.1,
      0.1,
      0.1,
      0.1009,
      0.1,
      0.1735,
      0.1,
      0.1,
      0.1,
      0.1,
      0.1,
      0.1,
      0.1,
      0.1,
      0.1,
      0.1,
      0.1,
      0.1003,
      0.1,
      0.1,
      0.1,
      0.1,
      0.1,
      0.1,
      0.1086,
      0.1,
      0.1567,
      0.1,
      0.138,
      0.1
    ],
    "accuracy_std": 0.021118230607700066,
    "worst_client_accuracy": 0.1,
    "global_loss": NaN,
    "honest_global_accuracy": 0.11059,
    "honest_accuracy_std": 0.023170582642652728,
    "honest_worst_accuracy": 0.1
  },
  {
    "round": 76,
    "elapsed_sec": 6013.670865058899,
    "cumulative_comm_bytes": 16856347200,
    "graph_updated": false,
    "graph_avg_degree": 14.76,
    "graph_spectral_gap": 2.4996758830522374,
    "graph_is_connected": true
  },
  {
    "round": 77,
    "elapsed_sec": 6082.497938632965,
    "cumulative_comm_bytes": 17075260800,
    "graph_updated": false,
    "graph_avg_degree": 14.76,
    "graph_spectral_gap": 2.4996758830522374,
    "graph_is_connected": true
  },
  {
    "round": 78,
    "elapsed_sec": 6146.614197254181,
    "cumulative_comm_bytes": 17294174400,
    "graph_updated": false,
    "graph_avg_degree": 14.76,
    "graph_spectral_gap": 2.4996758830522374,
    "graph_is_connected": true
  },
  {
    "round": 79,
    "elapsed_sec": 6204.407483100891,
    "cumulative_comm_bytes": 17513088000,
    "graph_updated": false,
    "graph_avg_degree": 14.76,
    "graph_spectral_gap": 2.4996758830522374,
    "graph_is_connected": true
  },
  {
    "round": 80,
    "elapsed_sec": 6340.757736444473,
    "cumulative_comm_bytes": 17732001600,
    "graph_updated": true,
    "graph_avg_degree": 15.16,
    "graph_spectral_gap": 2.522923318042948,
    "graph_is_connected": true,
    "global_accuracy": 0.11291599999999999,
    "per_client_accuracy": [
      0.1,
      0.1,
      0.1,
      0.1,
      0.1,
      0.1,
      0.1,
      0.1,
      0.1,
      0.1,
      0.1,
      0.1,
      0.1189,
      0.1751,
      0.1,
      0.1,
      0.1817,
      0.1682,
      0.1232,
      0.1,
      0.1847,
      0.2047,
      0.1,
      0.1,
      0.1001,
      0.1,
      0.1004,
      0.1,
      0.1,
      0.1,
      0.1,
      0.1,
      0.1,
      0.1,
      0.1,
      0.1523,
      0.1,
      0.1633,
      0.1,
      0.1,
      0.1,
      0.1,
      0.1,
      0.1028,
      0.1,
      0.1,
      0.1,
      0.1,
      0.1704,
      0.1
    ],
    "accuracy_std": 0.028058142205071235,
    "worst_client_accuracy": 0.1,
    "global_loss": NaN,
    "honest_global_accuracy": 0.11614500000000001,
    "honest_accuracy_std": 0.030527724694120257,
    "honest_worst_accuracy": 0.1
  },
  {
    "round": 81,
    "elapsed_sec": 6398.400186300278,
    "cumulative_comm_bytes": 17950915200,
    "graph_updated": false,
    "graph_avg_degree": 15.16,
    "graph_spectral_gap": 2.522923318042948,
    "graph_is_connected": true
  },
  {
    "round": 82,
    "elapsed_sec": 6465.763618469238,
    "cumulative_comm_bytes": 18169828800,
    "graph_updated": false,
    "graph_avg_degree": 15.16,
    "graph_spectral_gap": 2.522923318042948,
    "graph_is_connected": true
  },
  {
    "round": 83,
    "elapsed_sec": 6522.96493935585,
    "cumulative_comm_bytes": 18388742400,
    "graph_updated": false,
    "graph_avg_degree": 15.16,
    "graph_spectral_gap": 2.522923318042948,
    "graph_is_connected": true
  },
  {
    "round": 84,
    "elapsed_sec": 6580.2699291706085,
    "cumulative_comm_bytes": 18607656000,
    "graph_updated": false,
    "graph_avg_degree": 15.16,
    "graph_spectral_gap": 2.522923318042948,
    "graph_is_connected": true
  },
  {
    "round": 85,
    "elapsed_sec": 6721.522549152374,
    "cumulative_comm_bytes": 18826569600,
    "graph_updated": true,
    "graph_avg_degree": 15.8,
    "graph_spectral_gap": 2.912504908590906,
    "graph_is_connected": true,
    "global_accuracy": 0.11197999999999998,
    "per_client_accuracy": [
      0.1,
      0.1,
      0.1166,
      0.1,
      0.1,
      0.1,
      0.1,
      0.1956,
      0.1,
      0.1,
      0.1552,
      0.1,
      0.1192,
      0.1,
      0.1,
      0.1,
      0.1,
      0.1,
      0.1,
      0.1,
      0.1225,
      0.142,
      0.1,
      0.1,
      0.1704,
      0.1032,
      0.1,
      0.1,
      0.1,
      0.1728,
      0.1008,
      0.1,
      0.1,
      0.1,
      0.1,
      0.1398,
      0.1223,
      0.1719,
      0.1,
      0.1,
      0.1,
      0.1,
      0.1,
      0.1,
      0.1,
      0.1,
      0.1,
      0.1,
      0.1667,
      0.1
    ],
    "accuracy_std": 0.0244505787252572,
    "worst_client_accuracy": 0.1,
    "global_loss": NaN,
    "honest_global_accuracy": 0.11497500000000001,
    "honest_accuracy_std": 0.02650355400696291,
    "honest_worst_accuracy": 0.1
  },
  {
    "round": 86,
    "elapsed_sec": 6779.291758775711,
    "cumulative_comm_bytes": 19045483200,
    "graph_updated": false,
    "graph_avg_degree": 15.8,
    "graph_spectral_gap": 2.912504908590906,
    "graph_is_connected": true
  },
  {
    "round": 87,
    "elapsed_sec": 6844.5616862773895,
    "cumulative_comm_bytes": 19264396800,
    "graph_updated": false,
    "graph_avg_degree": 15.8,
    "graph_spectral_gap": 2.912504908590906,
    "graph_is_connected": true
  },
  {
    "round": 88,
    "elapsed_sec": 6913.5392463207245,
    "cumulative_comm_bytes": 19483310400,
    "graph_updated": false,
    "graph_avg_degree": 15.8,
    "graph_spectral_gap": 2.912504908590906,
    "graph_is_connected": true
  },
  {
    "round": 89,
    "elapsed_sec": 6971.04252243042,
    "cumulative_comm_bytes": 19702224000,
    "graph_updated": false,
    "graph_avg_degree": 15.8,
    "graph_spectral_gap": 2.912504908590906,
    "graph_is_connected": true
  },
  {
    "round": 90,
    "elapsed_sec": 7111.1006808280945,
    "cumulative_comm_bytes": 19921137600,
    "graph_updated": true,
    "graph_avg_degree": 17.16,
    "graph_spectral_gap": 3.087149630138403,
    "graph_is_connected": true,
    "global_accuracy": 0.108142,
    "per_client_accuracy": [
      0.1,
      0.1,
      0.1,
      0.1,
      0.1,
      0.1,
      0.1,
      0.1787,
      0.1436,
      0.1,
      0.1,
      0.1,
      0.1409,
      0.1271,
      0.1017,
      0.1,
      0.1,
      0.1,
      0.1241,
      0.1,
      0.1,
      0.1082,
      0.1,
      0.1,
      0.1,
      0.1383,
      0.1,
      0.1,
      0.1,
      0.1,
      0.1,
      0.1,
      0.1,
      0.1,
      0.1,
      0.1017,
      0.1,
      0.1707,
      0.1,
      0.1,
      0.1,
      0.1,
      0.1,
      0.1,
      0.1,
      0.1,
      0.1213,
      0.1,
      0.1508,
      0.1
    ],
    "accuracy_std": 0.018622997503087407,
    "worst_client_accuracy": 0.1,
    "global_loss": NaN,
    "honest_global_accuracy": 0.1101775,
    "honest_accuracy_std": 0.020317572289769267,
    "honest_worst_accuracy": 0.1
  },
  {
    "round": 91,
    "elapsed_sec": 7168.803978681564,
    "cumulative_comm_bytes": 20140051200,
    "graph_updated": false,
    "graph_avg_degree": 17.16,
    "graph_spectral_gap": 3.087149630138403,
    "graph_is_connected": true
  },
  {
    "round": 92,
    "elapsed_sec": 7229.292958498001,
    "cumulative_comm_bytes": 20358964800,
    "graph_updated": false,
    "graph_avg_degree": 17.16,
    "graph_spectral_gap": 3.087149630138403,
    "graph_is_connected": true
  },
  {
    "round": 93,
    "elapsed_sec": 7300.7341384887695,
    "cumulative_comm_bytes": 20577878400,
    "graph_updated": false,
    "graph_avg_degree": 17.16,
    "graph_spectral_gap": 3.087149630138403,
    "graph_is_connected": true
  },
  {
    "round": 94,
    "elapsed_sec": 7358.190398693085,
    "cumulative_comm_bytes": 20796792000,
    "graph_updated": false,
    "graph_avg_degree": 17.16,
    "graph_spectral_gap": 3.087149630138403,
    "graph_is_connected": true
  },
  {
    "round": 95,
    "elapsed_sec": 7494.471840143204,
    "cumulative_comm_bytes": 21015705600,
    "graph_updated": true,
    "graph_avg_degree": 16.8,
    "graph_spectral_gap": 2.968887757243648,
    "graph_is_connected": true,
    "global_accuracy": 0.10465999999999998,
    "per_client_accuracy": [
      0.1,
      0.1,
      0.1,
      0.1,
      0.1,
      0.1,
      0.1,
      0.1,
      0.1,
      0.1,
      0.1,
      0.1,
      0.1,
      0.1,
      0.1,
      0.1,
      0.1001,
      0.1,
      0.1,
      0.1,
      0.1125,
      0.1614,
      0.1,
      0.1,
      0.1578,
      0.1,
      0.1,
      0.1,
      0.1,
      0.1374,
      0.1,
      0.1,
      0.1,
      0.1,
      0.1,
      0.1001,
      0.1,
      0.1006,
      0.1,
      0.1,
      0.1631,
      0.1,
      0.1,
      0.1,
      0.1,
      0.1,
      0.1,
      0.1,
      0.1,
      0.1
    ],
    "accuracy_std": 0.015206590676413959,
    "worst_client_accuracy": 0.1,
    "global_loss": NaN,
    "honest_global_accuracy": 0.10582499999999999,
    "honest_accuracy_std": 0.01680072543076637,
    "honest_worst_accuracy": 0.1
  },
  {
    "round": 96,
    "elapsed_sec": 7552.209809303284,
    "cumulative_comm_bytes": 21234619200,
    "graph_updated": false,
    "graph_avg_degree": 16.8,
    "graph_spectral_gap": 2.968887757243648,
    "graph_is_connected": true
  },
  {
    "round": 97,
    "elapsed_sec": 7611.69716501236,
    "cumulative_comm_bytes": 21453532800,
    "graph_updated": false,
    "graph_avg_degree": 16.8,
    "graph_spectral_gap": 2.968887757243648,
    "graph_is_connected": true
  },
  {
    "round": 98,
    "elapsed_sec": 7672.827550649643,
    "cumulative_comm_bytes": 21672446400,
    "graph_updated": false,
    "graph_avg_degree": 16.8,
    "graph_spectral_gap": 2.968887757243648,
    "graph_is_connected": true
  },
  {
    "round": 99,
    "elapsed_sec": 7729.963020324707,
    "cumulative_comm_bytes": 21891360000,
    "graph_updated": false,
    "graph_avg_degree": 16.8,
    "graph_spectral_gap": 2.968887757243648,
    "graph_is_connected": true
  },
  {
    "round": 100,
    "elapsed_sec": 7863.976052522659,
    "cumulative_comm_bytes": 22110273600,
    "graph_updated": true,
    "graph_avg_degree": 16.44,
    "graph_spectral_gap": 3.014391298016628,
    "graph_is_connected": true,
    "global_accuracy": 0.10852199999999998,
    "per_client_accuracy": [
      0.1,
      0.1,
      0.1,
      0.1,
      0.1,
      0.1,
      0.1,
      0.1643,
      0.1,
      0.1,
      0.1,
      0.1036,
      0.1127,
      0.1684,
      0.1,
      0.1,
      0.1,
      0.1215,
      0.1,
      0.1,
      0.12,
      0.1,
      0.1,
      0.1,
      0.1511,
      0.1,
      0.1,
      0.1,
      0.1,
      0.1,
      0.1,
      0.1,
      0.1,
      0.1,
      0.1,
      0.1,
      0.1,
      0.1739,
      0.1,
      0.1,
      0.1007,
      0.1474,
      0.1,
      0.1068,
      0.1,
      0.1,
      0.1556,
      0.1,
      0.1001,
      0.1
    ],
    "accuracy_std": 0.01983713981399536,
    "worst_client_accuracy": 0.1,
    "global_loss": NaN,
    "honest_global_accuracy": 0.1106525,
    "honest_accuracy_std": 0.02166090934725502,
    "honest_worst_accuracy": 0.1
  },
  {
    "round": 101,
    "elapsed_sec": 7921.211688280106,
    "cumulative_comm_bytes": 22329187200,
    "graph_updated": false,
    "graph_avg_degree": 16.44,
    "graph_spectral_gap": 3.014391298016628,
    "graph_is_connected": true
  },
  {
    "round": 102,
    "elapsed_sec": 7978.442397117615,
    "cumulative_comm_bytes": 22548100800,
    "graph_updated": false,
    "graph_avg_degree": 16.44,
    "graph_spectral_gap": 3.014391298016628,
    "graph_is_connected": true
  },
  {
    "round": 103,
    "elapsed_sec": 8050.828018665314,
    "cumulative_comm_bytes": 22767014400,
    "graph_updated": false,
    "graph_avg_degree": 16.44,
    "graph_spectral_gap": 3.014391298016628,
    "graph_is_connected": true
  },
  {
    "round": 104,
    "elapsed_sec": 8109.298320531845,
    "cumulative_comm_bytes": 22985928000,
    "graph_updated": false,
    "graph_avg_degree": 16.44,
    "graph_spectral_gap": 3.014391298016628,
    "graph_is_connected": true
  },
  {
    "round": 105,
    "elapsed_sec": 8247.135119438171,
    "cumulative_comm_bytes": 23204841600,
    "graph_updated": true,
    "graph_avg_degree": 16.4,
    "graph_spectral_gap": 3.1702069126581884,
    "graph_is_connected": true,
    "global_accuracy": 0.109868,
    "per_client_accuracy": [
      0.1,
      0.1,
      0.1,
      0.1,
      0.1,
      0.1,
      0.1,
      0.1,
      0.12,
      0.1,
      0.1464,
      0.1,
      0.1,
      0.1615,
      0.1,
      0.1,
      0.1,
      0.1198,
      0.1188,
      0.1,
      0.156,
      0.1012,
      0.1,
      0.1,
      0.1,
      0.103,
      0.1,
      0.135,
      0.1,
      0.1,
      0.1,
      0.1,
      0.1,
      0.1,
      0.0995,
      0.1539,
      0.1,
      0.1606,
      0.1,
      0.1,
      0.1,
      0.1,
      0.1,
      0.1,
      0.1,
      0.1,
      0.1773,
      0.1081,
      0.1323,
      0.1
    ],
    "accuracy_std": 0.020122260707982093,
    "worst_client_accuracy": 0.0995,
    "global_loss": NaN,
    "honest_global_accuracy": 0.11233499999999999,
    "honest_accuracy_std": 0.021810577135876072,
    "honest_worst_accuracy": 0.0995
  },
  {
    "round": 106,
    "elapsed_sec": 8304.583322525024,
    "cumulative_comm_bytes": 23423755200,
    "graph_updated": false,
    "graph_avg_degree": 16.4,
    "graph_spectral_gap": 3.1702069126581884,
    "graph_is_connected": true
  },
  {
    "round": 107,
    "elapsed_sec": 8362.15108704567,
    "cumulative_comm_bytes": 23642668800,
    "graph_updated": false,
    "graph_avg_degree": 16.4,
    "graph_spectral_gap": 3.1702069126581884,
    "graph_is_connected": true
  },
  {
    "round": 108,
    "elapsed_sec": 8434.483630418777,
    "cumulative_comm_bytes": 23861582400,
    "graph_updated": false,
    "graph_avg_degree": 16.4,
    "graph_spectral_gap": 3.1702069126581884,
    "graph_is_connected": true
  },
  {
    "round": 109,
    "elapsed_sec": 8494.934310674667,
    "cumulative_comm_bytes": 24080496000,
    "graph_updated": false,
    "graph_avg_degree": 16.4,
    "graph_spectral_gap": 3.1702069126581884,
    "graph_is_connected": true
  },
  {
    "round": 110,
    "elapsed_sec": 8635.012113809586,
    "cumulative_comm_bytes": 24299409600,
    "graph_updated": true,
    "graph_avg_degree": 16.36,
    "graph_spectral_gap": 3.0572846052072933,
    "graph_is_connected": true,
    "global_accuracy": 0.10679599999999999,
    "per_client_accuracy": [
      0.1,
      0.1,
      0.1,
      0.1,
      0.1,
      0.1,
      0.1,
      0.1,
      0.1,
      0.1,
      0.1568,
      0.1,
      0.1223,
      0.194,
      0.1,
      0.1,
      0.1,
      0.1,
      0.1,
      0.1,
      0.1,
      0.1,
      0.1,
      0.157,
      0.1,
      0.1005,
      0.1,
      0.1,
      0.1,
      0.1,
      0.1,
      0.1,
      0.1,
      0.1,
      0.1,
      0.1,
      0.1,
      0.1803,
      0.1,
      0.1,
      0.1,
      0.1171,
      0.1,
      0.1,
      0.1,
      0.1,
      0.1,
      0.1,
      0.1118,
      0.1
    ],
    "accuracy_std": 0.020188729132860243,
    "worst_client_accuracy": 0.1,
    "global_loss": NaN,
    "honest_global_accuracy": 0.10849500000000001,
    "honest_accuracy_std": 0.02224967359311143,
    "honest_worst_accuracy": 0.1
  },
  {
    "round": 111,
    "elapsed_sec": 8692.728682041168,
    "cumulative_comm_bytes": 24518323200,
    "graph_updated": false,
    "graph_avg_degree": 16.36,
    "graph_spectral_gap": 3.0572846052072933,
    "graph_is_connected": true
  },
  {
    "round": 112,
    "elapsed_sec": 8750.240486383438,
    "cumulative_comm_bytes": 24737236800,
    "graph_updated": false,
    "graph_avg_degree": 16.36,
    "graph_spectral_gap": 3.0572846052072933,
    "graph_is_connected": true
  },
  {
    "round": 113,
    "elapsed_sec": 8820.811578512192,
    "cumulative_comm_bytes": 24956150400,
    "graph_updated": false,
    "graph_avg_degree": 16.36,
    "graph_spectral_gap": 3.0572846052072933,
    "graph_is_connected": true
  },
  {
    "round": 114,
    "elapsed_sec": 8883.498297214508,
    "cumulative_comm_bytes": 25175064000,
    "graph_updated": false,
    "graph_avg_degree": 16.36,
    "graph_spectral_gap": 3.0572846052072933,
    "graph_is_connected": true
  },
  {
    "round": 115,
    "elapsed_sec": 9023.845390081406,
    "cumulative_comm_bytes": 25393977600,
    "graph_updated": true,
    "graph_avg_degree": 16.8,
    "graph_spectral_gap": 3.3577396644676782,
    "graph_is_connected": true,
    "global_accuracy": 0.10391799999999998,
    "per_client_accuracy": [
      0.1,
      0.1,
      0.1045,
      0.1008,
      0.1,
      0.1,
      0.1,
      0.1,
      0.1,
      0.1,
      0.1001,
      0.1,
      0.1,
      0.1019,
      0.1,
      0.1,
      0.1,
      0.1604,
      0.1,
      0.1,
      0.1058,
      0.1,
      0.1,
      0.1116,
      0.1,
      0.1,
      0.1611,
      0.1001,
      0.1,
      0.1,
      0.1,
      0.1,
      0.1,
      0.1,
      0.1,
      0.1,
      0.1,
      0.1053,
      0.1,
      0.1,
      0.1443,
      0.1,
      0.1,
      0.1,
      0.1,
      0.1,
      0.1,
      0.1,
      0.1,
      0.1
    ],
    "accuracy_std": 0.013264338505933868,
    "worst_client_accuracy": 0.1,
    "global_loss": NaN,
    "honest_global_accuracy": 0.1048775,
    "honest_accuracy_std": 0.014673470746554815,
    "honest_worst_accuracy": 0.1
  },
  {
    "round": 116,
    "elapsed_sec": 9083.034502983093,
    "cumulative_comm_bytes": 25612891200,
    "graph_updated": false,
    "graph_avg_degree": 16.8,
    "graph_spectral_gap": 3.3577396644676782,
    "graph_is_connected": true
  },
  {
    "round": 117,
    "elapsed_sec": 9141.54615020752,
    "cumulative_comm_bytes": 25831804800,
    "graph_updated": false,
    "graph_avg_degree": 16.8,
    "graph_spectral_gap": 3.3577396644676782,
    "graph_is_connected": true
  },
  {
    "round": 118,
    "elapsed_sec": 9210.156069278717,
    "cumulative_comm_bytes": 26050718400,
    "graph_updated": false,
    "graph_avg_degree": 16.8,
    "graph_spectral_gap": 3.3577396644676782,
    "graph_is_connected": true
  },
  {
    "round": 119,
    "elapsed_sec": 9273.547521591187,
    "cumulative_comm_bytes": 26269632000,
    "graph_updated": false,
    "graph_avg_degree": 16.8,
    "graph_spectral_gap": 3.3577396644676782,
    "graph_is_connected": true
  },
  {
    "round": 120,
    "elapsed_sec": 9413.21454334259,
    "cumulative_comm_bytes": 26488545600,
    "graph_updated": true,
    "graph_avg_degree": 16.4,
    "graph_spectral_gap": 2.845222012475042,
    "graph_is_connected": true,
    "global_accuracy": 0.10864399999999998,
    "per_client_accuracy": [
      0.1,
      0.1,
      0.1563,
      0.1,
      0.1,
      0.1,
      0.1,
      0.1,
      0.102,
      0.1,
      0.1,
      0.1,
      0.1086,
      0.1278,
      0.1,
      0.1,
      0.1,
      0.1679,
      0.1,
      0.1,
      0.1,
      0.1467,
      0.1,
      0.1,
      0.1117,
      0.1,
      0.1006,
      0.1,
      0.1,
      0.1595,
      0.1,
      0.1,
      0.1,
      0.1,
      0.1,
      0.1,
      0.1,
      0.1443,
      0.1,
      0.1,
      0.1,
      0.1,
      0.1,
      0.1,
      0.1,
      0.1,
      0.1312,
      0.1,
      0.1756,
      0.1
    ],
    "accuracy_std": 0.01970007269022122,
    "worst_client_accuracy": 0.1,
    "global_loss": NaN,
    "honest_global_accuracy": 0.110805,
    "honest_accuracy_std": 0.02148875229044255,
    "honest_worst_accuracy": 0.1
  },
  {
    "round": 121,
    "elapsed_sec": 9470.478246450424,
    "cumulative_comm_bytes": 26707459200,
    "graph_updated": false,
    "graph_avg_degree": 16.4,
    "graph_spectral_gap": 2.845222012475042,
    "graph_is_connected": true
  },
  {
    "round": 122,
    "elapsed_sec": 9527.89972114563,
    "cumulative_comm_bytes": 26926372800,
    "graph_updated": false,
    "graph_avg_degree": 16.4,
    "graph_spectral_gap": 2.845222012475042,
    "graph_is_connected": true
  },
  {
    "round": 123,
    "elapsed_sec": 9593.664159059525,
    "cumulative_comm_bytes": 27145286400,
    "graph_updated": false,
    "graph_avg_degree": 16.4,
    "graph_spectral_gap": 2.845222012475042,
    "graph_is_connected": true
  },
  {
    "round": 124,
    "elapsed_sec": 9661.001892089844,
    "cumulative_comm_bytes": 27364200000,
    "graph_updated": false,
    "graph_avg_degree": 16.4,
    "graph_spectral_gap": 2.845222012475042,
    "graph_is_connected": true
  },
  {
    "round": 125,
    "elapsed_sec": 9801.903147935867,
    "cumulative_comm_bytes": 27583113600,
    "graph_updated": true,
    "graph_avg_degree": 16.52,
    "graph_spectral_gap": 2.83438562565964,
    "graph_is_connected": true,
    "global_accuracy": 0.11214399999999998,
    "per_client_accuracy": [
      0.1267,
      0.1,
      0.1,
      0.1585,
      0.1,
      0.1,
      0.1,
      0.1,
      0.1742,
      0.1,
      0.1,
      0.1,
      0.1205,
      0.2129,
      0.1,
      0.1,
      0.1,
      0.1,
      0.1398,
      0.1,
      0.1471,
      0.1,
      0.1,
      0.1187,
      0.1595,
      0.1884,
      0.1,
      0.1,
      0.1,
      0.1,
      0.1,
      0.1,
      0.1,
      0.1,
      0.1,
      0.1,
      0.134,
      0.1,
      0.1,
      0.1,
      0.1001,
      0.1,
      0.1,
      0.1,
      0.1,
      0.1,
      0.1268,
      0.1,
      0.1,
      0.1
    ],
    "accuracy_std": 0.025618275976341573,
    "worst_client_accuracy": 0.1,
    "global_loss": NaN,
    "honest_global_accuracy": 0.1137175,
    "honest_accuracy_std": 0.027036825696630882,
    "honest_worst_accuracy": 0.1
  },
  {
    "round": 126,
    "elapsed_sec": 9859.301941394806,
    "cumulative_comm_bytes": 27802027200,
    "graph_updated": false,
    "graph_avg_degree": 16.52,
    "graph_spectral_gap": 2.83438562565964,
    "graph_is_connected": true
  },
  {
    "round": 127,
    "elapsed_sec": 9916.661206007004,
    "cumulative_comm_bytes": 28020940800,
    "graph_updated": false,
    "graph_avg_degree": 16.52,
    "graph_spectral_gap": 2.83438562565964,
    "graph_is_connected": true
  },
  {
    "round": 128,
    "elapsed_sec": 9973.634803533554,
    "cumulative_comm_bytes": 28239854400,
    "graph_updated": false,
    "graph_avg_degree": 16.52,
    "graph_spectral_gap": 2.83438562565964,
    "graph_is_connected": true
  },
  {
    "round": 129,
    "elapsed_sec": 10045.038891077042,
    "cumulative_comm_bytes": 28458768000,
    "graph_updated": false,
    "graph_avg_degree": 16.52,
    "graph_spectral_gap": 2.83438562565964,
    "graph_is_connected": true
  },
  {
    "round": 130,
    "elapsed_sec": 10184.68321943283,
    "cumulative_comm_bytes": 28677681600,
    "graph_updated": true,
    "graph_avg_degree": 17.6,
    "graph_spectral_gap": 2.930458799496983,
    "graph_is_connected": true,
    "global_accuracy": 0.10871199999999998,
    "per_client_accuracy": [
      0.1409,
      0.1,
      0.1,
      0.1,
      0.1,
      0.1,
      0.1064,
      0.1,
      0.1,
      0.1,
      0.1445,
      0.1,
      0.122,
      0.1653,
      0.1,
      0.1,
      0.1,
      0.1,
      0.1,
      0.1,
      0.166,
      0.1,
      0.1,
      0.1,
      0.1,
      0.1,
      0.1,
      0.1,
      0.1,
      0.1,
      0.1,
      0.1,
      0.1,
      0.1,
      0.1,
      0.1,
      0.1566,
      0.1,
      0.1,
      0.1,
      0.1642,
      0.1697,
      0.1,
      0.1,
      0.1,
      0.1,
      0.1,
      0.1,
      0.1,
      0.1
    ],
    "accuracy_std": 0.02058468012867822,
    "worst_client_accuracy": 0.1,
    "global_loss": NaN,
    "honest_global_accuracy": 0.11089,
    "honest_accuracy_std": 0.022493174520285035,
    "honest_worst_accuracy": 0.1
  },
  {
    "round": 131,
    "elapsed_sec": 10241.945298910141,
    "cumulative_comm_bytes": 28896595200,
    "graph_updated": false,
    "graph_avg_degree": 17.6,
    "graph_spectral_gap": 2.930458799496983,
    "graph_is_connected": true
  },
  {
    "round": 132,
    "elapsed_sec": 10299.05782008171,
    "cumulative_comm_bytes": 29115508800,
    "graph_updated": false,
    "graph_avg_degree": 17.6,
    "graph_spectral_gap": 2.930458799496983,
    "graph_is_connected": true
  },
  {
    "round": 133,
    "elapsed_sec": 10356.879967451096,
    "cumulative_comm_bytes": 29334422400,
    "graph_updated": false,
    "graph_avg_degree": 17.6,
    "graph_spectral_gap": 2.930458799496983,
    "graph_is_connected": true
  },
  {
    "round": 134,
    "elapsed_sec": 10428.923128604889,
    "cumulative_comm_bytes": 29553336000,
    "graph_updated": false,
    "graph_avg_degree": 17.6,
    "graph_spectral_gap": 2.930458799496983,
    "graph_is_connected": true
  },
  {
    "round": 135,
    "elapsed_sec": 10565.790384292603,
    "cumulative_comm_bytes": 29772249600,
    "graph_updated": true,
    "graph_avg_degree": 17.12,
    "graph_spectral_gap": 2.758897164224793,
    "graph_is_connected": true,
    "global_accuracy": 0.11109399999999998,
    "per_client_accuracy": [
      0.1602,
      0.1,
      0.1,
      0.1,
      0.1,
      0.1,
      0.1,
      0.1809,
      0.1075,
      0.1,
      0.1001,
      0.1,
      0.1023,
      0.1832,
      0.1,
      0.1,
      0.1,
      0.1061,
      0.1,
      0.1,
      0.1,
      0.1101,
      0.1,
      0.1,
      0.1723,
      0.1,
      0.1,
      0.1031,
      0.1,
      0.1,
      0.1,
      0.1,
      0.1,
      0.1045,
      0.1004,
      0.1,
      0.1467,
      0.1485,
      0.1,
      0.1,
      0.1,
      0.142,
      0.1013,
      0.1,
      0.1,
      0.1,
      0.1682,
      0.1,
      0.1,
      0.1173
    ],
    "accuracy_std": 0.023513693116990364,
    "worst_client_accuracy": 0.1,
    "global_loss": NaN,
    "honest_global_accuracy": 0.11332249999999999,
    "honest_accuracy_std": 0.0256804545082442,
    "honest_worst_accuracy": 0.1
  },
  {
    "round": 136,
    "elapsed_sec": 10623.193373918533,
    "cumulative_comm_bytes": 29991163200,
    "graph_updated": false,
    "graph_avg_degree": 17.12,
    "graph_spectral_gap": 2.758897164224793,
    "graph_is_connected": true
  },
  {
    "round": 137,
    "elapsed_sec": 10680.374975442886,
    "cumulative_comm_bytes": 30210076800,
    "graph_updated": false,
    "graph_avg_degree": 17.12,
    "graph_spectral_gap": 2.758897164224793,
    "graph_is_connected": true
  },
  {
    "round": 138,
    "elapsed_sec": 10737.643218517303,
    "cumulative_comm_bytes": 30428990400,
    "graph_updated": false,
    "graph_avg_degree": 17.12,
    "graph_spectral_gap": 2.758897164224793,
    "graph_is_connected": true
  },
  {
    "round": 139,
    "elapsed_sec": 10805.946458339691,
    "cumulative_comm_bytes": 30647904000,
    "graph_updated": false,
    "graph_avg_degree": 17.12,
    "graph_spectral_gap": 2.758897164224793,
    "graph_is_connected": true
  },
  {
    "round": 140,
    "elapsed_sec": 10949.042874097824,
    "cumulative_comm_bytes": 30866817600,
    "graph_updated": true,
    "graph_avg_degree": 17.12,
    "graph_spectral_gap": 2.6773653056441034,
    "graph_is_connected": true,
    "global_accuracy": 0.11118999999999998,
    "per_client_accuracy": [
      0.1,
      0.1609,
      0.1,
      0.1,
      0.1,
      0.1,
      0.1095,
      0.1,
      0.1659,
      0.1,
      0.1,
      0.1,
      0.1471,
      0.126,
      0.1,
      0.1,
      0.1,
      0.1,
      0.1,
      0.1,
      0.1,
      0.2049,
      0.1,
      0.1,
      0.1524,
      0.1,
      0.1,
      0.1,
      0.1,
      0.1,
      0.1,
      0.1,
      0.1,
      0.1,
      0.1,
      0.1805,
      0.1,
      0.1021,
      0.1,
      0.1,
      0.1185,
      0.1149,
      0.1,
      0.1,
      0.1,
      0.1,
      0.1768,
      0.1,
      0.1,
      0.1
    ],
    "accuracy_std": 0.02508880427601124,
    "worst_client_accuracy": 0.1,
    "global_loss": NaN,
    "honest_global_accuracy": 0.11398749999999999,
    "honest_accuracy_std": 0.027343739571426582,
    "honest_worst_accuracy": 0.1
  },
  {
    "round": 141,
    "elapsed_sec": 11006.143611907959,
    "cumulative_comm_bytes": 31085731200,
    "graph_updated": false,
    "graph_avg_degree": 17.12,
    "graph_spectral_gap": 2.6773653056441034,
    "graph_is_connected": true
  },
  {
    "round": 142,
    "elapsed_sec": 11063.265493631363,
    "cumulative_comm_bytes": 31304644800,
    "graph_updated": false,
    "graph_avg_degree": 17.12,
    "graph_spectral_gap": 2.6773653056441034,
    "graph_is_connected": true
  },
  {
    "round": 143,
    "elapsed_sec": 11120.641389846802,
    "cumulative_comm_bytes": 31523558400,
    "graph_updated": false,
    "graph_avg_degree": 17.12,
    "graph_spectral_gap": 2.6773653056441034,
    "graph_is_connected": true
  },
  {
    "round": 144,
    "elapsed_sec": 11188.791156053543,
    "cumulative_comm_bytes": 31742472000,
    "graph_updated": false,
    "graph_avg_degree": 17.12,
    "graph_spectral_gap": 2.6773653056441034,
    "graph_is_connected": true
  },
  {
    "round": 145,
    "elapsed_sec": 11329.158487319946,
    "cumulative_comm_bytes": 31961385600,
    "graph_updated": true,
    "graph_avg_degree": 17.0,
    "graph_spectral_gap": 1.6992428470478977,
    "graph_is_connected": true,
    "global_accuracy": 0.11274199999999997,
    "per_client_accuracy": [
      0.1,
      0.1555,
      0.1,
      0.1,
      0.1,
      0.1,
      0.1,
      0.1,
      0.1,
      0.1,
      0.1829,
      0.1,
      0.1717,
      0.1,
      0.1,
      0.1,
      0.1,
      0.1,
      0.1,
      0.1,
      0.1,
      0.112,
      0.1,
      0.1218,
      0.1,
      0.1,
      0.1,
      0.1959,
      0.1,
      0.1,
      0.138,
      0.0998,
      0.1,
      0.1,
      0.1,
      0.1466,
      0.1171,
      0.1,
      0.1,
      0.1,
      0.1719,
      0.1721,
      0.1,
      0.1,
      0.1,
      0.1,
      0.1518,
      0.1,
      0.1,
      0.1
    ],
    "accuracy_std": 0.02598112460999331,
    "worst_client_accuracy": 0.0998,
    "global_loss": NaN,
    "honest_global_accuracy": 0.1159275,
    "honest_accuracy_std": 0.0281609036387329,
    "honest_worst_accuracy": 0.0998
  },
  {
    "round": 146,
    "elapsed_sec": 11386.696141242981,
    "cumulative_comm_bytes": 32180299200,
    "graph_updated": false,
    "graph_avg_degree": 17.0,
    "graph_spectral_gap": 1.6992428470478977,
    "graph_is_connected": true
  },
  {
    "round": 147,
    "elapsed_sec": 11443.716482877731,
    "cumulative_comm_bytes": 32399212800,
    "graph_updated": false,
    "graph_avg_degree": 17.0,
    "graph_spectral_gap": 1.6992428470478977,
    "graph_is_connected": true
  },
  {
    "round": 148,
    "elapsed_sec": 11500.776268005371,
    "cumulative_comm_bytes": 32618126400,
    "graph_updated": false,
    "graph_avg_degree": 17.0,
    "graph_spectral_gap": 1.6992428470478977,
    "graph_is_connected": true
  },
  {
    "round": 149,
    "elapsed_sec": 11565.694206953049,
    "cumulative_comm_bytes": 32837040000,
    "graph_updated": false,
    "graph_avg_degree": 17.0,
    "graph_spectral_gap": 1.6992428470478977,
    "graph_is_connected": true
  },
  {
    "round": 150,
    "elapsed_sec": 11716.05763053894,
    "cumulative_comm_bytes": 33055953600,
    "graph_updated": true,
    "graph_avg_degree": 17.6,
    "graph_spectral_gap": 2.250008122533008,
    "graph_is_connected": true,
    "global_accuracy": 0.10681399999999998,
    "per_client_accuracy": [
      0.1026,
      0.1,
      0.1,
      0.1,
      0.1,
      0.1,
      0.1768,
      0.1,
      0.1169,
      0.1,
      0.1708,
      0.1768,
      0.1,
      0.1001,
      0.1,
      0.1009,
      0.1,
      0.1001,
      0.1,
      0.1,
      0.1,
      0.1029,
      0.1,
      0.1,
      0.1525,
      0.1003,
      0.1386,
      0.1,
      0.1,
      0.1,
      0.1,
      0.1,
      0.1,
      0.1,
      0.1,
      0.1,
      0.1,
      0.1,
      0.1,
      0.1,
      0.1,
      0.1,
      0.0993,
      0.1021,
      0.1,
      0.1,
      0.1,
      0.1,
      0.1,
      0.1
    ],
    "accuracy_std": 0.019514302549668537,
    "worst_client_accuracy": 0.0993,
    "global_loss": NaN,
    "honest_global_accuracy": 0.1085175,
    "honest_accuracy_std": 0.0214825613870879,
    "honest_worst_accuracy": 0.0993
  },
  {
    "round": 151,
    "elapsed_sec": 11773.284925937653,
    "cumulative_comm_bytes": 33274867200,
    "graph_updated": false,
    "graph_avg_degree": 17.6,
    "graph_spectral_gap": 2.250008122533008,
    "graph_is_connected": true
  },
  {
    "round": 152,
    "elapsed_sec": 11830.31727719307,
    "cumulative_comm_bytes": 33493780800,
    "graph_updated": false,
    "graph_avg_degree": 17.6,
    "graph_spectral_gap": 2.250008122533008,
    "graph_is_connected": true
  },
  {
    "round": 153,
    "elapsed_sec": 11887.735419034958,
    "cumulative_comm_bytes": 33712694400,
    "graph_updated": false,
    "graph_avg_degree": 17.6,
    "graph_spectral_gap": 2.250008122533008,
    "graph_is_connected": true
  },
  {
    "round": 154,
    "elapsed_sec": 11951.768426179886,
    "cumulative_comm_bytes": 33931608000,
    "graph_updated": false,
    "graph_avg_degree": 17.6,
    "graph_spectral_gap": 2.250008122533008,
    "graph_is_connected": true
  },
  {
    "round": 155,
    "elapsed_sec": 12103.33396410942,
    "cumulative_comm_bytes": 34150521600,
    "graph_updated": true,
    "graph_avg_degree": 17.36,
    "graph_spectral_gap": 3.125100497292041,
    "graph_is_connected": true,
    "global_accuracy": 0.108888,
    "per_client_accuracy": [
      0.1035,
      0.1,
      0.1,
      0.1,
      0.1,
      0.1,
      0.1,
      0.127,
      0.1,
      0.1,
      0.1,
      0.1,
      0.1,
      0.1719,
      0.1,
      0.1,
      0.1,
      0.1722,
      0.1,
      0.1,
      0.1,
      0.1008,
      0.1,
      0.1,
      0.1623,
      0.1,
      0.1,
      0.1,
      0.1,
      0.1,
      0.1,
      0.1,
      0.1,
      0.1,
      0.1,
      0.144,
      0.1613,
      0.1,
      0.1,
      0.1,
      0.1189,
      0.182,
      0.1,
      0.1,
      0.1,
      0.1,
      0.1,
      0.1,
      0.1005,
      0.1
    ],
    "accuracy_std": 0.0218316068121428,
    "worst_client_accuracy": 0.1,
    "global_loss": NaN,
    "honest_global_accuracy": 0.11111,
    "honest_accuracy_std": 0.02389743500880377,
    "honest_worst_accuracy": 0.1
  },
  {
    "round": 156,
    "elapsed_sec": 12160.494615077972,
    "cumulative_comm_bytes": 34369435200,
    "graph_updated": false,
    "graph_avg_degree": 17.36,
    "graph_spectral_gap": 3.125100497292041,
    "graph_is_connected": true
  },
  {
    "round": 157,
    "elapsed_sec": 12217.591678142548,
    "cumulative_comm_bytes": 34588348800,
    "graph_updated": false,
    "graph_avg_degree": 17.36,
    "graph_spectral_gap": 3.125100497292041,
    "graph_is_connected": true
  },
  {
    "round": 158,
    "elapsed_sec": 12274.78518652916,
    "cumulative_comm_bytes": 34807262400,
    "graph_updated": false,
    "graph_avg_degree": 17.36,
    "graph_spectral_gap": 3.125100497292041,
    "graph_is_connected": true
  },
  {
    "round": 159,
    "elapsed_sec": 12335.888474941254,
    "cumulative_comm_bytes": 35026176000,
    "graph_updated": false,
    "graph_avg_degree": 17.36,
    "graph_spectral_gap": 3.125100497292041,
    "graph_is_connected": true
  },
  {
    "round": 160,
    "elapsed_sec": 12489.173819303513,
    "cumulative_comm_bytes": 35245089600,
    "graph_updated": true,
    "graph_avg_degree": 16.36,
    "graph_spectral_gap": 2.774689503316712,
    "graph_is_connected": true,
    "global_accuracy": 0.10805399999999998,
    "per_client_accuracy": [
      0.1,
      0.1,
      0.1,
      0.1003,
      0.1,
      0.1,
      0.1,
      0.1,
      0.1,
      0.1,
      0.1091,
      0.1,
      0.1,
      0.1,
      0.1,
      0.1,
      0.1,
      0.1,
      0.1,
      0.1,
      0.1,
      0.1693,
      0.1,
      0.1064,
      0.1022,
      0.1043,
      0.1,
      0.1,
      0.1,
      0.1,
      0.1,
      0.1,
      0.1,
      0.1,
      0.1,
      0.1499,
      0.1784,
      0.1491,
      0.1,
      0.1,
      0.1075,
      0.1,
      0.1,
      0.1,
      0.1,
      0.1,
      0.1649,
      0.1,
      0.1613,
      0.1
    ],
    "accuracy_std": 0.020386105169943568,
    "worst_client_accuracy": 0.1,
    "global_loss": NaN,
    "honest_global_accuracy": 0.11006,
    "honest_accuracy_std": 0.0223465746815927,
    "honest_worst_accuracy": 0.1
  },
  {
    "round": 161,
    "elapsed_sec": 12546.64549446106,
    "cumulative_comm_bytes": 35464003200,
    "graph_updated": false,
    "graph_avg_degree": 16.36,
    "graph_spectral_gap": 2.774689503316712,
    "graph_is_connected": true
  }
]